odb2vtk/__init__.py
odb2vtk/__main__.py
odb2vtk/_version.py
odb2vtk/multiprocess.py
odb2vtk/odb2vtk.py
odb2vtk-1.0.0.dist-info/LICENSE
odb2vtk-1.0.0.dist-info/METADATA
odb2vtk-1.0.0.dist-info/WHEEL
odb2vtk-1.0.0.dist-info/entry_points.txt
odb2vtk-1.0.0.dist-info/top_level.txt
odb2vtk-1.0.0.dist-info/RECORD
