Metadata-Version: 2.1
Name: odb2vtk
Version: 1.0.0
Summary: ODB2VTK converter
Author-email: WANG Hailin <hailin.wang@connect.polyu.hk>
Project-URL: GitHub, https://github.com/haiiliin/odb2vtk
Classifier: Programming Language :: Python
Classifier: Programming Language :: Python :: 3
Classifier: License :: OSI Approved :: MIT License
Classifier: Operating System :: OS Independent
Requires-Python: >=3.7
License-File: LICENSE
Requires-Dist: abqpy
Requires-Dist: numpy
